geofinder_vt/ImageExtractor.py
geofinder_vt/VideoConverter.py
geofinder_vt/__init__.py
geofinder_vt/gpmf_support.py
geofinder_vt-0.3.1.dist-info/LICENSE
geofinder_vt-0.3.1.dist-info/METADATA
geofinder_vt-0.3.1.dist-info/WHEEL
geofinder_vt-0.3.1.dist-info/top_level.txt
geofinder_vt-0.3.1.dist-info/RECORD
