Metadata-Version: 2.1
Name: geofinder-vt
Version: 0.3.1
Summary: A brief description of your package
Home-page: https://github.com/nathan846/geofindervt
Author: Your Name
Author-email: vaidhyanathan@vt.edu
Classifier: Programming Language :: Python :: 3
Classifier: License :: OSI Approved :: MIT License
Classifier: Operating System :: OS Independent
License-File: LICENSE
Requires-Dist: geocoder (==1.38.1)
Requires-Dist: geopy (==2.3.0)
Requires-Dist: gpmf (==0.1)
Requires-Dist: gpxpy (==1.5.0)
Requires-Dist: lxml (==4.9.2)
Requires-Dist: moviepy (>=1.0.3)
Requires-Dist: numpy (>=1.19.3)
Requires-Dist: pandas (>=1.1.3)
Requires-Dist: python-dateutil (>=2.8.2)
Requires-Dist: pytz (>=2023.3)
Requires-Dist: pywin32 (>=306)
Requires-Dist: typing-extensions (==4.6.0)
Requires-Dist: xmltodict (==0.13.0)
